colorstats/Photo.py
colorstats/Photoset.py
colorstats/__init__.py
colorstats-1.2.0.dist-info/LICENSE.txt
colorstats-1.2.0.dist-info/METADATA
colorstats-1.2.0.dist-info/WHEEL
colorstats-1.2.0.dist-info/top_level.txt
colorstats-1.2.0.dist-info/RECORD
