Metadata-Version: 2.1
Name: colorstats
Version: 1.2.0
Summary: Package for processing color data from images
Home-page: https://github.com/nramkissoon/ColorStats
Author: Nicholas Ramkissoon
License: UNKNOWN
Platform: UNKNOWN
Classifier: Intended Audience :: Developers
Classifier: Programming Language :: Python :: 3
Classifier: License :: OSI Approved :: MIT License
Classifier: Operating System :: OS Independent
Requires-Python: >=3
